fidder/__init__.py
fidder/_cli.py
fidder/constants.py
fidder/train.py
fidder/utils.py
fidder/_tests/test_utils.py
fidder/data/__init__.py
fidder/data/augmentation.py
fidder/data/download.py
fidder/data/training_datamodule.py
fidder/data/training_dataset.py
fidder/data/_tests/__init__.py
fidder/data/_tests/test_download_data.py
fidder/erase/__init__.py
fidder/erase/cli.py
fidder/erase/erase.py
fidder/erase/sparse_local_mean.py
fidder/erase/_tests/test_erasing.py
fidder/model/__init__.py
fidder/model/_pretrained_weights.py
fidder/model/dice.py
fidder/model/model.py
fidder/model/model_parts.py
fidder/model/_tests/test_dice.py
fidder/model/_tests/test_download_checkpoint.py
fidder/model/_tests/test_model.py
fidder/predict/__init__.py
fidder/predict/cli.py
fidder/predict/predict.py
fidder/predict/probabilities_to_mask.py
fidder-0.0.8.dist-info/METADATA
fidder-0.0.8.dist-info/WHEEL
fidder-0.0.8.dist-info/entry_points.txt
fidder-0.0.8.dist-info/licenses/LICENSE
fidder-0.0.8.dist-info/RECORD
