Metadata-Version: 2.1
Name: fidder
Version: 0.0.8
Summary: U-Net for 2D fiducial segmentation in cryo-EM
Project-URL: homepage, https://github.com/teamtomo/fidder
Project-URL: repository, https://github.com/teamtomo/fidder
Author: Alister Burt
Author-email: alisterburt@gmail.com
License: BSD 3-Clause License
License-File: LICENSE
Classifier: Development Status :: 3 - Alpha
Classifier: License :: OSI Approved :: BSD License
Classifier: Programming Language :: Python :: 3
Classifier: Programming Language :: Python :: 3.8
Classifier: Programming Language :: Python :: 3.9
Classifier: Programming Language :: Python :: 3.10
Requires-Python: >=3.8
Requires-Dist: einops
Requires-Dist: imageio
Requires-Dist: mrcfile
Requires-Dist: numpy
Requires-Dist: pooch
Requires-Dist: pytorch-lightning
Requires-Dist: rich
Requires-Dist: scipy
Requires-Dist: tiler
Requires-Dist: torch
Requires-Dist: torchvision
Requires-Dist: typer
Requires-Dist: zenodo-get
Provides-Extra: dev
Requires-Dist: black; extra == 'dev'
Requires-Dist: ipython; extra == 'dev'
Requires-Dist: mkdocs-material; extra == 'dev'
Requires-Dist: mypy; extra == 'dev'
Requires-Dist: pdbpp; extra == 'dev'
Requires-Dist: pre-commit; extra == 'dev'
Requires-Dist: pytest; extra == 'dev'
Requires-Dist: pytest-cov; extra == 'dev'
Requires-Dist: rich; extra == 'dev'
Requires-Dist: ruff; extra == 'dev'
Provides-Extra: test
Requires-Dist: pytest-cov; extra == 'test'
Requires-Dist: pytest>=6.0; extra == 'test'
